giturl/__init__.py
giturl/exceptions.py
giturl/schema.py
giturl/test/__init__.py
giturl/test/test_parse.py
giturl-0.1.3.dist-info/LICENSE
giturl-0.1.3.dist-info/METADATA
giturl-0.1.3.dist-info/WHEEL
giturl-0.1.3.dist-info/top_level.txt
giturl-0.1.3.dist-info/RECORD
