Metadata-Version: 2.1
Name: giturl
Version: 0.1.3
Summary: Parsing and validating git urls.
Home-page: https://gitlab.com/divio/incubator/giturl
Author: Divio AG
Author-email: dennis.schwertel@divio.ch
License: BSD
Platform: UNKNOWN
Classifier: Development Status :: 4 - Beta
Classifier: Intended Audience :: Developers
Classifier: Operating System :: OS Independent
Classifier: Programming Language :: Python
Classifier: Programming Language :: Python :: 3
Classifier: Programming Language :: Python :: 3.6
Classifier: Programming Language :: Python :: 3.7
Classifier: Programming Language :: Python :: 3.8
Classifier: Programming Language :: Python :: 3.9
Requires-Dist: attrs
Requires-Dist: pyparsing
